[
  {
    "category": "Computer",
    "title": "HTML & CSS Basics",
    "readTime": { "value": 35, "unit": "minute" },
    "author": {
      "name": "JON DUCKETT",
      "avatar": "https://ui-avatars.com/api/?name=Jon+Duckett"
    },
    "content": "HTML",
    "_id": "c1muqc6lepp5de4",
    "createdAt": "2023-03-01T13:11:34.156Z",
    "updatedAt": "2023-03-01T13:18:42.286Z",
    "comments": [
      {
        "text": "erfghjytr",
        "createdAt": "2023-03-03T13:13:31.439Z",
        "updatedAt": "2023-03-03T13:13:31.439Z",
        "_id": "c1mu1bo9lesk3l80"
      },
      {
        "text": "test",
        "createdAt": "2023-03-03T13:18:39.089Z",
        "updatedAt": "2023-03-03T13:18:39.089Z",
        "_id": "c1mu1bqlleska6lu"
      }
    ],
    "avatar": "http://localhost:3001/img/blogPosts/c1muqc6lepp5de4.png",
    "cover": "https://res.cloudinary.com/dgfcfb0rr/image/upload/v1678127814/Strive/blogCover/av8it8nufp4jiqeyxuyf.jpg"
  },
  {
    "category": "Computer",
    "title": "NodeJS Basics",
    "readTime": { "value": 50, "unit": "minute" },
    "author": {
      "name": "Kevin Pasquali",
      "avatar": "https://ui-avatars.com/api/?name=Kevin+Pasquali"
    },
    "content": "node js",
    "_id": "c1muqjgleppl5e3",
    "createdAt": "2023-03-01T13:23:50.282Z",
    "updatedAt": "2023-03-01T15:50:22.159Z",
    "comments": [
      {
        "comment": "test",
        "author": "farhana",
        "createdAt": "2023-03-05T10:22:29.632Z",
        "updatedAt": "2023-03-05T10:22:29.632Z",
        "_id": "c1mu1cj1lev8vcht"
      }
    ],
    "cover": "https://res.cloudinary.com/dgfcfb0rr/image/upload/v1678127882/Strive/blogCover/dwknbowwkew0uhooob2k.jpg"
  },
  {
    "category": "Computer",
    "title": "JS Basics",
    "readTime": { "value": 50, "unit": "minute" },
    "author": {
      "name": "JON DUCKETT",
      "avatar": "https://ui-avatars.com/api/?name=Jon+Duckett"
    },
    "content": "JavaScript",
    "_id": "c1muqu7leppv8bn",
    "createdAt": "2023-03-01T13:31:40.642Z",
    "updatedAt": "2023-03-01T13:31:40.642Z",
    "comments": [
      {
        "text": "testsdfgewszsdxf",
        "createdAt": "2023-03-03T13:20:31.166Z",
        "updatedAt": "2023-03-03T13:20:31.166Z",
        "_id": "c1mu1bqlleskcl32"
      }
    ],
    "cover": "https://res.cloudinary.com/dgfcfb0rr/image/upload/v1678127947/Strive/blogCover/j0ufnkoi6zxwiidw7tdw.jpg"
  },
  {
    "category": "Computer",
    "title": "Basics of JS",
    "readTime": { "value": 50, "unit": "minute" },
    "author": {
      "name": "Kevin John",
      "avatar": "https://ui-avatars.com/api/?name=Kevin+John"
    },
    "content": "basics",
    "_id": "c1mu116uler3sx3l",
    "createdAt": "2023-03-02T12:49:33.584Z",
    "updatedAt": "2023-03-02T12:49:33.584Z",
    "comments": [],
    "cover": "https://res.cloudinary.com/dgfcfb0rr/image/upload/v1678128045/Strive/blogCover/cokz5lzcy827ihi1aq9x.jpg"
  },
  {
    "category": "HTML",
    "title": "Html",
    "cover": "https://res.cloudinary.com/dgfcfb0rr/image/upload/v1678128138/Strive/blogCover/q9vmuiadwx8aytrqvhdd.jpg",
    "readTime": { "value": "19", "unit": "minute" },
    "author": {
      "name": "FARHANA RAFI",
      "avatar": "https://ui-avatars.com/api/?name=Farhana+Rafi"
    },
    "content": "<p>wdfsdgfhgfd</p>",
    "_id": "c1mu1cj1lev8x2kw",
    "createdAt": "2023-03-05T10:23:50.096Z",
    "updatedAt": "2023-03-05T10:23:50.096Z"
  },
  {
    "category": "HTML",
    "title": "Html",
    "cover": "https://picsum.photos/800/400",
    "readTime": { "value": "12", "unit": "minute" },
    "author": {
      "name": "FARHANA RAFI",
      "avatar": "https://ui-avatars.com/api/?name=Farhana+Rafi"
    },
    "content": "<p>sdfghj</p>",
    "_id": "c1mu1cj1lev8xvhf",
    "createdAt": "2023-03-05T10:24:27.555Z",
    "updatedAt": "2023-03-05T10:24:27.555Z"
  }
]
